resistify/__init__.py
resistify/annotations.py
resistify/hmmsearch.py
resistify/main.py
resistify/nlrexpress.py
resistify/utility.py
resistify/data/MLP_CC_extEDVID.pkl
resistify/data/MLP_LRR_LxxLxL.pkl
resistify/data/MLP_NBS_GLPL.pkl
resistify/data/MLP_NBS_MHD.pkl
resistify/data/MLP_NBS_P-loop.pkl
resistify/data/MLP_NBS_RNSB-A.pkl
resistify/data/MLP_NBS_RNSB-B.pkl
resistify/data/MLP_NBS_RNSB-C.pkl
resistify/data/MLP_NBS_RNSB-D.pkl
resistify/data/MLP_NBS_VG.pkl
resistify/data/MLP_NBS_Walker-B.pkl
resistify/data/MLP_TIR_aA.pkl
resistify/data/MLP_TIR_aC.pkl
resistify/data/MLP_TIR_aD3.pkl
resistify/data/MLP_TIR_bA.pkl
resistify/data/MLP_TIR_bC.pkl
resistify/data/MLP_TIR_bD-aD1.pkl
resistify/data/nlrdb.hmm
resistify/data/nlrexpress.fasta
resistify-0.4.0.dist-info/METADATA
resistify-0.4.0.dist-info/WHEEL
resistify-0.4.0.dist-info/entry_points.txt
resistify-0.4.0.dist-info/licenses/LICENSE
resistify-0.4.0.dist-info/RECORD
