Metadata-Version: 2.3
Name: resistify
Version: 0.4.0
Summary: A resistance gene annotation tool
Author-email: Moray Smith <moraysmith98@gmail.com>
License-File: LICENSE
Classifier: License :: OSI Approved :: MIT License
Classifier: Operating System :: OS Independent
Classifier: Programming Language :: Python :: 3
Requires-Python: >=3.9
Requires-Dist: biopython
Requires-Dist: numpy<1.23.0
Requires-Dist: rich
Requires-Dist: rich-argparse
Requires-Dist: scikit-learn==0.24.2
